<?xml version = "1.0" encoding = "UTF-8"?>
<!DOCTYPE suite SYSTEM "http://testng.org/testng-1.0.dtd" >

<suite name = "Orders tests">
    <test name = "Check buy product">
        <parameter name = "Data" value="src\\test\\data\\orders.json"/>
        <parameter name="email" value="test1@test.com1"/>
        <parameter name="password" value="TestPassword1"/>
        <classes>
            <class name="tests.OrdersTests">
                <methods>
                    <include name="addProductToCartWith"/>
                </methods>
            </class>
        </classes>
    </test>
</suite>